pywander_text/__init__.py
pywander_text/__main__.py
pywander_text/country_zh_abbr.py
pywander_text/encoding.py
pywander_text/line.py
pywander_text/pandoc.py
pywander_text/pinyin.py
pywander_text/process_text.py
pywander_text/stopwords.py
pywander_text/tc_sc.py
pywander_text/web.py
pywander_text/zh_number.py
pywander_text/html/index.html
pywander_text/html/css/bootstrap.min.css
pywander_text/html/css/main.css
pywander_text/html/js/bootstrap.bundle.min.js
pywander_text/html/js/main.js
pywander_text/ref_scripts/__init__.py
pywander_text/ref_scripts/modify_line_to_tex_chapter.py
pywander_text/ref_scripts/re_replace.py
pywander_text/ref_scripts/remove_english_line.py
pywander_text/ref_scripts/remove_redundant_blank_line.py
pywander_text/ref_scripts/remove_unwanted_parts.py
pywander_text-0.2.1.dist-info/licenses/LICENSE
pywander_text-0.2.1.dist-info/METADATA
pywander_text-0.2.1.dist-info/WHEEL
pywander_text-0.2.1.dist-info/entry_points.txt
pywander_text-0.2.1.dist-info/top_level.txt
pywander_text-0.2.1.dist-info/RECORD
