Metadata-Version: 2.4
Name: pywander-text
Version: 0.2.1
Summary: 文本处理工具集.
Home-page: https://github.com/a358003542/pywander-text
Author: wander
Author-email: a358003542@outlook.com
Maintainer: wander
Maintainer-email: a358003542@outlook.com
License: MIT
Keywords: python
Classifier: Operating System :: Microsoft
Classifier: Operating System :: POSIX :: Linux
Classifier: Programming Language :: Python :: 3
License-File: LICENSE
Requires-Dist: click
Requires-Dist: pywander
Requires-Dist: pyparsing
Requires-Dist: pypinyin
Requires-Dist: opencc
Requires-Dist: fastapi
Requires-Dist: uvicorn
Requires-Dist: tabulate
Dynamic: license-file
